StdioBridge/__init__.py
StdioBridge/_config.py
StdioBridge/_ui/expandable_widget.py
StdioBridge/_ui/main_window.py
StdioBridge/_ui/request_item.py
StdioBridge/_ui/search.py
StdioBridge/api/__init__.py
StdioBridge/api/_api.py
StdioBridge/api/_docs.py
StdioBridge/api/_response.py
StdioBridge/api/_router.py
StdioBridge/api/errors.py
StdioBridge/client/__init__.py
StdioBridge/client/_client.py
StdioBridge/client/_response.py
StdioBridge-1.3.3.dist-info/LICENSE
StdioBridge-1.3.3.dist-info/METADATA
StdioBridge-1.3.3.dist-info/WHEEL
StdioBridge-1.3.3.dist-info/entry_points.txt
StdioBridge-1.3.3.dist-info/top_level.txt
StdioBridge-1.3.3.dist-info/RECORD
