Metadata-Version: 2.1
Name: StdioBridge
Version: 1.3.3
Summary: A StdioBridge package.
Home-page: https://github.com/SergeiKrivko
Author: SergeiKrivko
License: MIT License
Requires-Python: >=3.10
License-File: LICENSE
Requires-Dist: aioconsole ~=0.7.1
